cli_charts/__init__.py
cli_charts/cli-charts.py
cli_charts/for-bar.py
cli_charts-0.0.1.dist-info/LICENCE
cli_charts-0.0.1.dist-info/METADATA
cli_charts-0.0.1.dist-info/WHEEL
cli_charts-0.0.1.dist-info/top_level.txt
cli_charts-0.0.1.dist-info/RECORD
